Metadata-Version: 2.1
Name: thiccboimath
Version: 1.0
Summary: A simple python math function package.
Home-page: https://github.com/Thickduck/pymath/tree/main/Python%20maths%20project/Math%20operators
Author: ThickduckPlayz
Author-email: iamhackerboi8@gmail.com
License: GNU GENERAL PUBLIC LICENSE
Download-URL: https://github.com/Thickduck/pymath/archive/refs/tags/1.0.tar.gz
Keywords: pypi,thiccboimath,math
Platform: UNKNOWN
Classifier: Development Status :: 3 - Alpha
Classifier: Intended Audience :: Developers
Classifier: Topic :: Software Development :: Documentation
Classifier: Programming Language :: Python :: 3
Classifier: Programming Language :: Python :: 3.7
Classifier: Programming Language :: Python :: 3.8
Classifier: Programming Language :: Python :: 3.9
License-File: LICENSE.txt
